{
  "baseUrl": "https://raw.githubusercontent.com/Miguel080902/CodeaMiningMultiMedia/master/images",
  "backgroundImage": "https://raw.githubusercontent.com/Miguel080902/CodeaMiningMultiMedia/master/images/backgrounds/tech-circuit-pattern.png",
  "images": [
    {
      "id": "1",
      "src": "about/about-1.jpg",
      "alt": "Momento del evento CODEa Mining Fest",
      "category": "evento",
      "title": "Networking",
      "description": "Profesionales de la industria minera compartiendo experiencias y creando nuevas conexiones."
    },
    {
      "id": "2",
      "src": "about/about-2.jpg",
      "alt": "Asistentes del evento",
      "category": "evento",
      "title": "Audiencia Comprometida",
      "description": "Más de 500 asistentes participando activamente en las conferencias."
    },
    {
      "id": "3",
      "src": "about/about-3.jpg",
      "alt": "Presentación en vivo",
      "category": "evento",
      "title": "Presentaciones Magistrales",
      "description": "Expertos compartiendo las últimas tendencias en tecnología minera."
    },
    {
      "id": "4",
      "src": "about/about-4.jpg",
      "alt": "Ambiente del evento",
      "category": "evento",
      "title": "Ambiente Profesional",
      "description": "Un espacio diseñado para el intercambio de conocimientos y networking."
    },
    {
      "id": "6",
      "src": "contact/mining-engineer-woman.png",
      "alt": "Ingeniera de minas",
      "category": "evento",
      "title": "Diversidad en la Minería",
      "description": "Profesionales de todas las áreas participando en el evento."
    },
    {
      "id": "7",
      "src": "highlights/panel-discussion.jpg",
      "alt": "Panel de discusión",
      "category": "evento",
      "title": "Panel de Discusión",
      "description": "Mesa redonda con expertos discutiendo el futuro de la minería."
    },
    {
      "id": "8",
      "src": "keynotes/keynote-alessandra.png",
      "alt": "Keynote Alessandra",
      "category": "keynotes",
      "title": "Dra. Alessandra Silva",
      "description": "Keynote: \"Innovación y Sostenibilidad en la Minería del Futuro\""
    },
    {
      "id": "9",
      "src": "keynotes/keynote-alexander.png",
      "alt": "Keynote Alexander",
      "category": "keynotes",
      "title": "Dr. Alexander Torres",
      "description": "Keynote: \"Transformación Digital en Operaciones Mineras\""
    },
    {
      "id": "10",
      "src": "keynotes/keynote-cleber.png",
      "alt": "Keynote Cleber",
      "category": "keynotes",
      "title": "Ing. Cleber Rodríguez",
      "description": "Keynote: \"Automatización y Robótica en la Industria Minera\""
    },
    {
      "id": "11",
      "src": "keynotes/keynote-felipe.png",
      "alt": "Keynote Felipe",
      "category": "keynotes",
      "title": "Dr. Felipe Martínez",
      "description": "Keynote: \"Inteligencia Artificial aplicada a la Geología\""
    },
    {
      "id": "13",
      "src": "keynotes/keynote-kevin.png",
      "alt": "Keynote Kevin",
      "category": "keynotes",
      "title": "Dr. Kevin Johnson",
      "description": "Keynote: \"Machine Learning para Optimización de Procesos\""
    },
    {
      "id": "16",
      "src": "speakers/speaker-christa.png",
      "alt": "Speaker Christa",
      "category": "ponentes",
      "title": "Dra. Christa Anderson",
      "description": "Especialista en Sostenibilidad Minera"
    },
    {
      "id": "17",
      "src": "speakers/speaker-christian.png",
      "alt": "Speaker Christian",
      "category": "ponentes",
      "title": "Ing. Christian Müller",
      "description": "Experto en Tecnologías de Extracción"
    },
    {
      "id": "18",
      "src": "speakers/speaker-hyder.png",
      "alt": "Speaker Hyder",
      "category": "ponentes",
      "title": "Dr. Hyder Khan",
      "description": "Investigador en Procesamiento de Minerales"
    },
    {
      "id": "19",
      "src": "speakers/speaker-leonardo.png",
      "alt": "Speaker Leonardo",
      "category": "ponentes",
      "title": "Ing. Leonardo Castro",
      "description": "Consultor en Optimización de Operaciones"
    },
    {
      "id": "20",
      "src": "testimonial/IMG_3293.jpg",
      "alt": "Testimonio participante",
      "category": "testimonios",
      "title": "Momento de Networking",
      "description": "Participantes intercambiando experiencias durante el evento"
    },
    {
      "id": "21",
      "src": "testimonial/testimonial-catherine.jpg",
      "alt": "Testimonio Catherine",
      "category": "testimonios",
      "title": "Catherine Williams",
      "description": "\"Una experiencia transformadora para mi carrera en minería\""
    },
    {
      "id": "22",
      "src": "testimonial/testimonial-luis.png",
      "alt": "Testimonio Luis",
      "category": "testimonios",
      "title": "Luis Fernández",
      "description": "\"Excelente oportunidad para conocer las últimas tendencias\""
    },
    {
      "id": "23",
      "src": "testimonial/testimonial-yair.png",
      "alt": "Testimonio Yair",
      "category": "testimonios",
      "title": "Yair González",
      "description": "\"Networking invaluable con profesionales de toda Latinoamérica\""
    },
    {
      "id": "24",
      "src": "about/evento-whatsapp-image-2025-08-12-at-1-1755530323286.jpeg",
      "alt": "prueba",
      "category": "evento",
      "title": "Prueba de optimizacion",
      "description": "prueba"
    }
  ]
}